{
  "generatedAt": "2026-03-24T21:29:48.437Z",
  "startTime": "2026-03-24T21:28:37.264Z",
  "endTime": "2026-03-24T21:29:47.623Z",
  "deployId": "dep-d71g48i4d50c73bnetl0",
  "mode": "balanced",
  "escalated": false,
  "fetch": {
    "initialLimit": 200,
    "fullLimit": 200,
    "rowsFetchedInitial": 55,
    "rowsFetchedExpanded": 0
  },
  "totals": {
    "rows": 55,
    "bySeverity": {
      "info": 55,
      "warn": 0,
      "error": 0,
      "fatal": 0
    },
    "repoAccessWarningCount": 0,
    "truncatedTypes": []
  },
  "thresholds": {
    "maxWarnings": 0,
    "maxErrors": 0,
    "maxRepoWarnings": 0,
    "failOnTruncation": true
  },
  "types": {
    "build": {
      "rows": 18,
      "hasMore": false
    },
    "app": {
      "rows": 37,
      "hasMore": false
    }
  },
  "severeSamples": []
}
